jfc/__init__.py
jfc/helper.py
jfc/jfc.py
jfc-3.4.4.6.dist-info/entry_points.txt
jfc-3.4.4.6.dist-info/LICENSE
jfc-3.4.4.6.dist-info/WHEEL
jfc-3.4.4.6.dist-info/METADATA
jfc-3.4.4.6.dist-info/RECORD
