Metadata-Version: 2.1
Name: jfc
Version: 3.4.4.6
Summary: Jina Flow Companion - search and index from the CLI
Home-page: https://github.com/alexcg1/jfc
License: Apache-2.0
Keywords: Jina,search
Author: Alex C-G
Author-email: alex.cg@jina.ai
Requires-Python: >=3.7,<4.0
Classifier: License :: OSI Approved :: Apache Software License
Classifier: Programming Language :: Python :: 3
Classifier: Programming Language :: Python :: 3.10
Classifier: Programming Language :: Python :: 3.7
Classifier: Programming Language :: Python :: 3.8
Classifier: Programming Language :: Python :: 3.9
Requires-Dist: jina (>=3.0,<4.0)
Project-URL: Repository, https://github.com/alexcg1/jfc
